rsrc_local/__init__.py
rsrc_local/base.py
rsrc_local/hints.py
rsrc_local/models.py
rsrc_local-0.1.2.dist-info/LICENSE
rsrc_local-0.1.2.dist-info/METADATA
rsrc_local-0.1.2.dist-info/WHEEL
rsrc_local-0.1.2.dist-info/entry_points.txt
rsrc_local-0.1.2.dist-info/top_level.txt
rsrc_local-0.1.2.dist-info/RECORD
