Metadata-Version: 2.1
Name: rsrc-local
Version: 0.1.2
Summary: `rsrc` plugin for working with local/local network resources.
Home-page: https://github.com/lycantropos/rsrc_local/
Author: Azat Ibrakov
Author-email: azatibrakov@gmail.com
License: UNKNOWN
Download-URL: https://github.com/lycantropos/rsrc_local/archive/master.zip
Platform: UNKNOWN
Requires-Python: >=3.5.3
Requires-Dist: memoir (>=0.0.3)
Requires-Dist: reprit (>=0.3.0)
Requires-Dist: rsrc (>=0.1.3)
